README.md
setup.cfg
setup.py
zeno_distributions/Binomialdistribution.py
zeno_distributions/Gaussiandistribution.py
zeno_distributions/Generaldistribution.py
zeno_distributions/__init__.py
zeno_distributions.egg-info/PKG-INFO
zeno_distributions.egg-info/SOURCES.txt
zeno_distributions.egg-info/dependency_links.txt
zeno_distributions.egg-info/not-zip-safe
zeno_distributions.egg-info/top_level.txt