Metadata-Version: 1.0
Name: zeno-distributions
Version: 0.1
Summary: Gaussian and Binomial distributions
Home-page: UNKNOWN
Author: ChangSu LEE
Author-email: UNKNOWN
License: UNKNOWN
Platform: UNKNOWN
